moveev_common/__init__.py
moveev_common/charging_event.py
moveev_common/charging_session.py
moveev_common/charging_stat.py
moveev_common/client.py
moveev_common/client_service.py
moveev_common/credential.py
moveev_common/event_log.py
moveev_common/last_run_time.py
moveev_common/location.py
moveev_common/service.py
moveev_common/vehicle.py
moveev_common-0.2.2.dist-info/LICENSE
moveev_common-0.2.2.dist-info/METADATA
moveev_common-0.2.2.dist-info/WHEEL
moveev_common-0.2.2.dist-info/top_level.txt
moveev_common-0.2.2.dist-info/RECORD
