Metadata-Version: 2.1
Name: moveev-common
Version: 0.2.2
Summary: Common utilities for MoveEV projects
Author-email: Fabricio Pavano <faripavano@gmail.com>
License: MIT
Classifier: Programming Language :: Python :: 3
Classifier: Operating System :: OS Independent
Requires-Python: >=3.10
License-File: LICENSE
Requires-Dist: sqlalchemy>=1.4
Requires-Dist: pydantic>=1.8
